{
  "project_info": {
    "project_number": "284502733106",
    "project_id": "danzify-2a2ec",
    "storage_bucket": "danzify-2a2ec.appspot.com"
  },
  "client": [
    {
      "client_info": {
        "mobilesdk_app_id": "1:284502733106:android:bfab9abd3860bc5bad272b",
        "android_client_info": {
          "package_name": "com.example.quiz"
        }
      },
      "oauth_client": [],
      "api_key": [
        {
          "current_key": "AIzaSyD-uhkQZ6ZyR8ElYqG0QJ_8G1yNi4ewjJ4"
        }
      ],
      "services": {
        "appinvite_service": {
          "other_platform_oauth_client": []
        }
      }
    }
  ],
  "configuration_version": "1"
}